{"cameraMode":{"drawMode":0,"name":"Shaded","section":"Shading Mode"},"sceneLighting":true,"audioPlay":false,"sceneViewState":{"showFog":true,"showMaterialUpdate":false,"showSkybox":true,"showFlares":true,"showImageEffects":true,"showParticleSystems":true,"showVisualEffectGraphs":true,"m_FxEnabled":true},"in2DMode":false,"pivot":{"x":-22.81728744506836,"y":38.93800354003906,"z":-13.886608123779297},"rotation":{"x":0.6078788042068481,"y":0.1503417044878006,"z":-0.11850479990243912,"w":0.7707170248031616},"size":0.8320507407188416,"orthographic":false}